python_criteria/__init__.py
python_criteria/attribute.py
python_criteria/clauses.py
python_criteria/constraints.py
python_criteria/entity.py
python_criteria/filter.py
python_criteria/label.py
python_criteria/memory.py
python_criteria/sqlalchemy.py
python_criteria/visitor.py
python_criteria-0.11.1.dist-info/LICENSE
python_criteria-0.11.1.dist-info/METADATA
python_criteria-0.11.1.dist-info/WHEEL
python_criteria-0.11.1.dist-info/top_level.txt
python_criteria-0.11.1.dist-info/RECORD
